Metadata-Version: 1.0
Name: rootfetch
Version: 0.0.2
Summary: command line program for downloading various certificate root stores
Home-page: UNKNOWN
Author: ZMap Team
Author-email: zmap-team@umich.edu
License: Apache License, Version 2.0
Keywords: python json schema bigquery elastic search
Platform: UNKNOWN
